sherali_adams/__init__.py
sherali_adams/sherali_adams.py
sherali_adams-0.2.dist-info/LICENSE
sherali_adams-0.2.dist-info/METADATA
sherali_adams-0.2.dist-info/WHEEL
sherali_adams-0.2.dist-info/top_level.txt
sherali_adams-0.2.dist-info/RECORD
