Metadata-Version: 2.1
Name: sherali-adams
Version: 0.2
Summary: run k rounds of SA hierarchy
Home-page: http://github.com/knavely/sherali_adams
Author: Matthew Drescher
Author-email: knavely@gmail.com
License: Apache 2.0
Keywords: integer programming mip sherali-adams optimization
Platform: UNKNOWN
Requires-Dist: numpy
